[{"name":"P0FiA7WWC","marks":71},{"name":"iPdrmr","marks":77},{"name":"PwsvKZmZV","marks":69},{"name":"Qh","marks":94},{"name":"F91Go","marks":68},{"name":"f","marks":13},{"name":"BmJs","marks":34},{"name":"fk599fs5","marks":85},{"name":"snNGzd7","marks":26},{"name":"uspVLyCi","marks":3},{"name":"AGFNMcNJ","marks":20},{"name":"uFw8","marks":57},{"name":"eeYLdMt","marks":36},{"name":"nQKJXiHXb7","marks":88},{"name":"6MmMJZAF","marks":38},{"name":"aGN0l","marks":78},{"name":"th4T","marks":87},{"name":"E3hfD","marks":96},{"name":"512AQKDRLp","marks":43},{"name":"34TbCX","marks":63},{"name":"ESNZf","marks":69},{"name":"3IA7AeOinE","marks":60},{"name":"rvqjZF","marks":17},{"name":"Oie","marks":28},{"name":"W7","marks":66},{"name":"ta6plB","marks":32},{"name":"vv8i","marks":97},{"name":"VwROldStE","marks":23},{"name":"BLfQ3PoZCf","marks":53},{"name":"2eGHtOTzEi","marks":58},{"name":"ZqmsP0v7o","marks":99},{"name":"uMRbhmY","marks":80},{"name":"Ai4","marks":61},{"name":"C","marks":21},{"name":"4lDw","marks":13},{"name":"1xciq","marks":61},{"name":"8qJhzz","marks":78},{"name":"FJ","marks":91},{"name":"fSlZVtGc","marks":68},{"name":"OswWc1","marks":9},{"name":"56fxdFEB","marks":15},{"name":"D","marks":6},{"name":"RJjuc","marks":89},{"name":"k7PX","marks":68},{"name":"egGqrtFLF","marks":64},{"name":"GWCNq","marks":60},{"name":"vCAZUNr","marks":2},{"name":"n","marks":6},{"name":"w","marks":25},{"name":"AC1zODBCM","marks":1},{"name":"MeD","marks":17},{"name":"2HGQ","marks":56},{"name":"P72","marks":73},{"name":"lNsJda","marks":76},{"name":"9q7","marks":52},{"name":"Qew","marks":64},{"name":"MB34jtp","marks":67},{"name":"Mt9H4DhUk2","marks":19},{"name":"LJyj7T1nT","marks":68},{"name":"weWHFnP","marks":39},{"name":"TKCu6dK","marks":52},{"name":"o8cmmkRsT","marks":0},{"name":"mCEf","marks":48},{"name":"gbjRG9E","marks":56},{"name":"Fzl","marks":39},{"name":"mDGs6EuJU","marks":64},{"name":"Cg1yReIGqA","marks":9},{"name":"hxtixP7nOc","marks":6},{"name":"yS1zM","marks":94},{"name":"4WmLe1BoSh","marks":48},{"name":"ju1pUQIX2","marks":14},{"name":"JwiHhx","marks":71},{"name":"zhCcGeD","marks":5},{"name":"56","marks":69},{"name":"Avg16mzcM2","marks":47},{"name":"RJ8J48c1e6","marks":14},{"name":"SkTTv","marks":27},{"name":"OfXVc","marks":68},{"name":"zBwfsCOOi9","marks":11},{"name":"Hme","marks":84},{"name":"0I0a8de4Ic","marks":24},{"name":"23wrwCg2Z","marks":95},{"name":"KBgzxLRX0","marks":36},{"name":"Xd9fq5zq","marks":86},{"name":"QUi25m","marks":78},{"name":"C2","marks":3},{"name":"h6fcep","marks":69},{"name":"jsbD3kqU","marks":23},{"name":"V","marks":0},{"name":"wP","marks":33},{"name":"yq","marks":83},{"name":"TAXLD7","marks":80},{"name":"RLYl8S","marks":28},{"name":"s1K1EDrW","marks":29},{"name":"VELqHkDOIu","marks":14},{"name":"8","marks":63},{"name":"PlaQQ0TIDQ","marks":15},{"name":"PjN0FZ","marks":30},{"name":"HKv0sBNC9t","marks":97},{"name":"id7GvLAlg","marks":92}]